README.md
algorthm
setup.py
algorthm/__init__.py
algorthm.egg-info/PKG-INFO
algorthm.egg-info/SOURCES.txt
algorthm.egg-info/dependency_links.txt
algorthm.egg-info/top_level.txt
algorthm/search/__init__.py
algorthm/search/binraysearch.py
algorthm/search/linearsearch.py