Metadata-Version: 2.1
Name: algorthm
Version: 0.1
Summary: A package for studying various Algorithms and visualizing the operations 
Home-page: https://github.com/dinaklal/algorthm
Author: Dinak Lal
Author-email: dinaklal@gmail.com
License: UNKNOWN
Platform: UNKNOWN
Classifier: Programming Language :: Python :: 3
Classifier: License :: OSI Approved :: MIT License
Classifier: Operating System :: OS Independent
